main.py
lens_grove_cli-0.2.0.dist-info/licenses/LICENSE
modules/db.py
modules/fileops.py
modules/filesdb.py
modules/lens.py
modules/wallet.py
lens_grove_cli-0.2.0.dist-info/METADATA
lens_grove_cli-0.2.0.dist-info/WHEEL
lens_grove_cli-0.2.0.dist-info/entry_points.txt
lens_grove_cli-0.2.0.dist-info/top_level.txt
lens_grove_cli-0.2.0.dist-info/RECORD
