Metadata-Version: 2.4
Name: lens-grove-cli
Version: 0.2.0
Summary: A command line interface for the Lens Grove storage network
Author-email: LittleBit <littlebit@littlebitstudios.com>
License: MIT
Classifier: Programming Language :: Python :: 3
Classifier: License :: OSI Approved :: MIT License
Classifier: Operating System :: OS Independent
Classifier: Topic :: System :: Archiving :: Mirroring
Classifier: Intended Audience :: Developers
Requires-Python: >=3.10
License-File: LICENSE
Requires-Dist: web3
Requires-Dist: pyyaml
Requires-Dist: requests
Requires-Dist: randomname
Requires-Dist: tabulate
Dynamic: license-file
